README.rst
setup.py
firebase/__init__.py
firebase/async.py
firebase/decorators.py
firebase/firebase.py
firebase/firebase_token_generator.py
firebase/jsonutil.py
firebase/lazy.py
python_firebase_gae.egg-info/PKG-INFO
python_firebase_gae.egg-info/SOURCES.txt
python_firebase_gae.egg-info/dependency_links.txt
python_firebase_gae.egg-info/not-zip-safe
python_firebase_gae.egg-info/requires.txt
python_firebase_gae.egg-info/top_level.txt