Metadata-Version: 1.1
Name: python-firebase-gae
Version: 1.0.0
Summary: Python interface to the Firebase's REST API.
Home-page: http://ozgur.github.com/python-firebase/
Author: Oshane Bailey
Author-email: b4.oshany@gmail.com
License: MIT
Keywords: firebase python gae google appengine
Platform: UNKNOWN
Classifier: Development Status :: 5 - Production/Stable
Classifier: Environment :: Console
Classifier: Intended Audience :: Developers
Classifier: License :: OSI Approved :: MIT License
Classifier: Operating System :: OS Independent
Classifier: Programming Language :: Python :: 2.6
Classifier: Programming Language :: Python :: 2.7
Classifier: Programming Language :: Python :: 3.2
Classifier: Natural Language :: English
